{
  "__inputs": [
    {
      "name": "DS_SCALE_CLUSTER_2_5.1.1.1",
      "label": "scale_cluster_2_5.1.1.1",
      "description": "",
      "type": "datasource",
      "pluginId": "opentsdb",
      "pluginName": "OpenTSDB"
    },
    {
      "name": "DS_SCALE_5.1.0-3",
      "label": "scale_5.1.0-3",
      "description": "",
      "type": "datasource",
      "pluginId": "opentsdb",
      "pluginName": "OpenTSDB"
    }
  ],
  "__requires": [
    {
      "type": "grafana",
      "id": "grafana",
      "name": "Grafana",
      "version": "7.5.1"
    },
    {
      "type": "panel",
      "id": "graph",
      "name": "Graph",
      "version": ""
    },
    {
      "type": "datasource",
      "id": "opentsdb",
      "name": "OpenTSDB",
      "version": "1.0.0"
    },
    {
      "type": "panel",
      "id": "stat",
      "name": "Stat",
      "version": ""
    }
  ],
  "annotations": {
    "list": [
      {
        "builtIn": 1,
        "datasource": "-- Grafana --",
        "enable": true,
        "hide": true,
        "iconColor": "rgba(0, 211, 255, 1)",
        "name": "Annotations & Alerts",
        "type": "dashboard"
      }
    ]
  },
  "editable": true,
  "gnetId": null,
  "graphTooltip": 0,
  "id": null,
  "iteration": 1620737071023,
  "links": [
    {
      "asDropdown": false,
      "icon": "external link",
      "includeVars": false,
      "keepTime": false,
      "tags": [
        "home"
      ],
      "targetBlank": false,
      "title": "",
      "tooltip": "",
      "type": "dashboards",
      "url": ""
    }
  ],
  "panels": [
    {
      "aliasColors": {},
      "bars": true,
      "dashLength": 10,
      "dashes": false,
      "datasource": "${DS_SCALE_CLUSTER_2_5.1.1.1}",
      "fieldConfig": {
        "defaults": {
          "unit": "bytes"
        },
        "overrides": []
      },
      "fill": 1,
      "fillGradient": 0,
      "gridPos": {
        "h": 8,
        "w": 11,
        "x": 0,
        "y": 0
      },
      "hiddenSeries": false,
      "id": 31,
      "legend": {
        "avg": false,
        "current": false,
        "max": false,
        "min": false,
        "show": true,
        "total": false,
        "values": false
      },
      "lines": false,
      "linewidth": 1,
      "nullPointMode": "null",
      "options": {
        "alertThreshold": false
      },
      "percentage": false,
      "pluginVersion": "7.5.1",
      "pointradius": 2,
      "points": false,
      "renderer": "flot",
      "seriesOverrides": [],
      "spaceLength": 10,
      "stack": true,
      "steppedLine": false,
      "targets": [
        {
          "aggregator": "noop",
          "alias": "$tag_node",
          "currentFilterGroupBy": false,
          "currentFilterKey": "",
          "currentFilterType": null,
          "currentFilterValue": "",
          "disableDownsampling": true,
          "downsampleAggregator": "noop",
          "downsampleFillPolicy": "none",
          "filters": [
            {
              "filter": "$gateWayNode",
              "groupBy": false,
              "tagk": "node",
              "type": "pm_filter"
            },
            {
              "filter": "$afmFS",
              "groupBy": false,
              "tagk": "gpfs_fs_name",
              "type": "pm_filter"
            }
          ],
          "metric": "gpfs_afm_fs_bytes_written",
          "refId": "A"
        }
      ],
      "thresholds": [],
      "timeFrom": null,
      "timeRegions": [],
      "timeShift": null,
      "title": "$afmFS (number of bytes written)",
      "tooltip": {
        "shared": true,
        "sort": 0,
        "value_type": "individual"
      },
      "type": "graph",
      "xaxis": {
        "buckets": null,
        "mode": "time",
        "name": null,
        "show": true,
        "values": []
      },
      "yaxes": [
        {
          "format": "bytes",
          "label": null,
          "logBase": 1,
          "max": null,
          "min": null,
          "show": true
        },
        {
          "format": "short",
          "label": null,
          "logBase": 1,
          "max": null,
          "min": null,
          "show": true
        }
      ],
      "yaxis": {
        "align": false,
        "alignLevel": null
      }
    },
    {
      "aliasColors": {},
      "bars": true,
      "dashLength": 10,
      "dashes": false,
      "datasource": "${DS_SCALE_CLUSTER_2_5.1.1.1}",
      "fieldConfig": {
        "defaults": {
          "unit": "short"
        },
        "overrides": []
      },
      "fill": 1,
      "fillGradient": 0,
      "gridPos": {
        "h": 8,
        "w": 12,
        "x": 11,
        "y": 0
      },
      "hiddenSeries": false,
      "id": 32,
      "legend": {
        "avg": false,
        "current": false,
        "max": false,
        "min": false,
        "show": true,
        "total": false,
        "values": false
      },
      "lines": false,
      "linewidth": 1,
      "nullPointMode": "null",
      "options": {
        "alertThreshold": false
      },
      "percentage": false,
      "pluginVersion": "7.5.1",
      "pointradius": 2,
      "points": false,
      "renderer": "flot",
      "seriesOverrides": [],
      "spaceLength": 10,
      "stack": true,
      "steppedLine": false,
      "targets": [
        {
          "aggregator": "noop",
          "alias": "$tag_node",
          "currentFilterGroupBy": false,
          "currentFilterKey": "",
          "currentFilterType": null,
          "currentFilterValue": "",
          "disableDownsampling": true,
          "downsampleAggregator": "noop",
          "downsampleFillPolicy": "none",
          "filters": [
            {
              "filter": "$afmFS",
              "groupBy": false,
              "tagk": "gpfs_fs_name",
              "type": "pm_filter"
            },
            {
              "filter": "$gateWayNode",
              "groupBy": false,
              "tagk": "node",
              "type": "pm_filter"
            }
          ],
          "metric": "gpfs_afm_fs_ops_sent",
          "refId": "A"
        }
      ],
      "thresholds": [],
      "timeFrom": null,
      "timeRegions": [],
      "timeShift": null,
      "title": "$afmFS (number of operations sent)",
      "tooltip": {
        "shared": true,
        "sort": 0,
        "value_type": "individual"
      },
      "type": "graph",
      "xaxis": {
        "buckets": null,
        "mode": "time",
        "name": null,
        "show": true,
        "values": []
      },
      "yaxes": [
        {
          "format": "short",
          "label": null,
          "logBase": 1,
          "max": null,
          "min": null,
          "show": true
        },
        {
          "format": "short",
          "label": null,
          "logBase": 1,
          "max": null,
          "min": null,
          "show": true
        }
      ],
      "yaxis": {
        "align": false,
        "alignLevel": null
      }
    },
    {
      "aliasColors": {},
      "bars": true,
      "dashLength": 10,
      "dashes": false,
      "datasource": "${DS_SCALE_CLUSTER_2_5.1.1.1}",
      "fieldConfig": {
        "defaults": {
          "unit": "bytes"
        },
        "overrides": []
      },
      "fill": 2,
      "fillGradient": 2,
      "gridPos": {
        "h": 9,
        "w": 11,
        "x": 0,
        "y": 8
      },
      "hiddenSeries": false,
      "id": 33,
      "legend": {
        "avg": false,
        "current": false,
        "max": false,
        "min": false,
        "show": true,
        "total": false,
        "values": false
      },
      "lines": false,
      "linewidth": 3,
      "nullPointMode": "null as zero",
      "options": {
        "alertThreshold": false
      },
      "percentage": false,
      "pluginVersion": "7.5.1",
      "pointradius": 5,
      "points": false,
      "renderer": "flot",
      "seriesOverrides": [],
      "spaceLength": 10,
      "stack": true,
      "steppedLine": false,
      "targets": [
        {
          "aggregator": "noop",
          "alias": "$tag_node",
          "currentFilterGroupBy": false,
          "currentFilterKey": "",
          "currentFilterType": "literal_or",
          "currentFilterValue": "",
          "disableDownsampling": true,
          "downsampleAggregator": "noop",
          "downsampleFillPolicy": "none",
          "downsampleInterval": "",
          "filters": [
            {
              "filter": "$afmFS",
              "groupBy": true,
              "tagk": "gpfs_fs_name",
              "type": "pm_filter"
            },
            {
              "filter": "$gateWayNode",
              "groupBy": false,
              "tagk": "node",
              "type": "pm_filter"
            }
          ],
          "metric": "gpfs_afm_fs_used_q_memory",
          "refId": "A"
        }
      ],
      "thresholds": [],
      "timeFrom": null,
      "timeRegions": [],
      "timeShift": null,
      "title": "$afmFS (used memory in bytes by the messages queued)",
      "tooltip": {
        "shared": true,
        "sort": 0,
        "value_type": "individual"
      },
      "type": "graph",
      "xaxis": {
        "buckets": null,
        "mode": "time",
        "name": null,
        "show": true,
        "values": []
      },
      "yaxes": [
        {
          "format": "bytes",
          "label": null,
          "logBase": 1,
          "max": null,
          "min": null,
          "show": true
        },
        {
          "format": "short",
          "label": null,
          "logBase": 1,
          "max": null,
          "min": null,
          "show": true
        }
      ],
      "yaxis": {
        "align": false,
        "alignLevel": null
      }
    },
    {
      "aliasColors": {},
      "bars": true,
      "dashLength": 10,
      "dashes": false,
      "datasource": "${DS_SCALE_CLUSTER_2_5.1.1.1}",
      "fieldConfig": {
        "defaults": {
          "unit": "bytes"
        },
        "overrides": []
      },
      "fill": 2,
      "fillGradient": 2,
      "gridPos": {
        "h": 9,
        "w": 12,
        "x": 11,
        "y": 8
      },
      "hiddenSeries": false,
      "id": 9,
      "legend": {
        "avg": false,
        "current": false,
        "max": false,
        "min": false,
        "show": true,
        "total": false,
        "values": false
      },
      "lines": false,
      "linewidth": 3,
      "nullPointMode": "null as zero",
      "options": {
        "alertThreshold": false
      },
      "percentage": false,
      "pluginVersion": "7.5.1",
      "pointradius": 5,
      "points": false,
      "renderer": "flot",
      "seriesOverrides": [],
      "spaceLength": 10,
      "stack": true,
      "steppedLine": false,
      "targets": [
        {
          "aggregator": "noop",
          "alias": "$tag_node",
          "currentFilterGroupBy": false,
          "currentFilterKey": "",
          "currentFilterType": "literal_or",
          "currentFilterValue": "",
          "disableDownsampling": true,
          "downsampleAggregator": "noop",
          "downsampleFillPolicy": "none",
          "downsampleInterval": "",
          "filters": [
            {
              "filter": "$afmFS",
              "groupBy": true,
              "tagk": "gpfs_fs_name",
              "type": "pm_filter"
            },
            {
              "filter": "$gateWayNode",
              "groupBy": false,
              "tagk": "node",
              "type": "pm_filter"
            }
          ],
          "metric": "gpfs_afm_fs_num_queued_msgs",
          "refId": "A"
        }
      ],
      "thresholds": [],
      "timeFrom": null,
      "timeRegions": [],
      "timeShift": null,
      "title": "$afmFS (number of messages that are currently queued)",
      "tooltip": {
        "shared": true,
        "sort": 0,
        "value_type": "individual"
      },
      "type": "graph",
      "xaxis": {
        "buckets": null,
        "mode": "time",
        "name": null,
        "show": true,
        "values": []
      },
      "yaxes": [
        {
          "format": "bytes",
          "label": null,
          "logBase": 1,
          "max": null,
          "min": null,
          "show": true
        },
        {
          "format": "short",
          "label": null,
          "logBase": 1,
          "max": null,
          "min": null,
          "show": true
        }
      ],
      "yaxis": {
        "align": false,
        "alignLevel": null
      }
    },
    {
      "collapsed": true,
      "datasource": "${DS_SCALE_5.1.0-3}",
      "gridPos": {
        "h": 1,
        "w": 24,
        "x": 0,
        "y": 17
      },
      "id": 27,
      "panels": [
        {
          "datasource": "${DS_SCALE_CLUSTER_2_5.1.1.1}",
          "fieldConfig": {
            "defaults": {
              "color": {
                "mode": "palette-classic"
              },
              "mappings": [],
              "thresholds": {
                "mode": "absolute",
                "steps": [
                  {
                    "color": "green",
                    "value": null
                  },
                  {
                    "color": "red",
                    "value": 80
                  }
                ]
              },
              "unit": "bytes"
            },
            "overrides": []
          },
          "gridPos": {
            "h": 7,
            "w": 6,
            "x": 0,
            "y": 18
          },
          "id": 24,
          "options": {
            "colorMode": "value",
            "graphMode": "area",
            "justifyMode": "auto",
            "orientation": "auto",
            "reduceOptions": {
              "calcs": [
                "lastNotNull"
              ],
              "fields": "",
              "values": false
            },
            "text": {},
            "textMode": "auto"
          },
          "pluginVersion": "7.5.1",
          "targets": [
            {
              "aggregator": "sum",
              "currentFilterGroupBy": false,
              "currentFilterKey": "",
              "currentFilterType": null,
              "currentFilterValue": "",
              "disableDownsampling": true,
              "downsampleAggregator": "noop",
              "downsampleFillPolicy": "none",
              "filters": [
                {
                  "filter": "$gateWayNode",
                  "groupBy": false,
                  "tagk": "node",
                  "type": "pm_filter"
                },
                {
                  "filter": "$afmFS",
                  "groupBy": false,
                  "tagk": "gpfs_fs_name",
                  "type": "pm_filter"
                }
              ],
              "metric": "gpfs_afm_fs_bytes_read",
              "refId": "A"
            }
          ],
          "timeFrom": null,
          "timeShift": null,
          "title": "Total number of bytes read",
          "type": "stat"
        },
        {
          "datasource": "${DS_SCALE_CLUSTER_2_5.1.1.1}",
          "fieldConfig": {
            "defaults": {
              "color": {
                "mode": "palette-classic"
              },
              "mappings": [],
              "thresholds": {
                "mode": "absolute",
                "steps": [
                  {
                    "color": "green",
                    "value": null
                  },
                  {
                    "color": "red",
                    "value": 80
                  }
                ]
              },
              "unit": "bytes"
            },
            "overrides": []
          },
          "gridPos": {
            "h": 7,
            "w": 6,
            "x": 6,
            "y": 18
          },
          "id": 29,
          "options": {
            "colorMode": "value",
            "graphMode": "area",
            "justifyMode": "auto",
            "orientation": "auto",
            "reduceOptions": {
              "calcs": [
                "lastNotNull"
              ],
              "fields": "",
              "values": false
            },
            "text": {},
            "textMode": "auto"
          },
          "pluginVersion": "7.5.1",
          "targets": [
            {
              "aggregator": "sum",
              "currentFilterGroupBy": false,
              "currentFilterKey": "",
              "currentFilterType": null,
              "currentFilterValue": "",
              "disableDownsampling": true,
              "downsampleAggregator": "noop",
              "downsampleFillPolicy": "none",
              "filters": [
                {
                  "filter": "$gateWayNode",
                  "groupBy": false,
                  "tagk": "node",
                  "type": "pm_filter"
                },
                {
                  "filter": "$afmFS",
                  "groupBy": false,
                  "tagk": "gpfs_fs_name",
                  "type": "pm_filter"
                }
              ],
              "metric": "gpfs_afm_fs_bytes_written",
              "refId": "A"
            }
          ],
          "timeFrom": null,
          "timeShift": null,
          "title": "Total number of bytes written",
          "type": "stat"
        },
        {
          "datasource": "${DS_SCALE_CLUSTER_2_5.1.1.1}",
          "fieldConfig": {
            "defaults": {
              "color": {
                "mode": "palette-classic"
              },
              "mappings": [],
              "thresholds": {
                "mode": "absolute",
                "steps": [
                  {
                    "color": "green",
                    "value": null
                  },
                  {
                    "color": "red",
                    "value": 80
                  }
                ]
              },
              "unit": "bytes"
            },
            "overrides": []
          },
          "gridPos": {
            "h": 7,
            "w": 6,
            "x": 12,
            "y": 18
          },
          "id": 30,
          "options": {
            "colorMode": "value",
            "graphMode": "area",
            "justifyMode": "auto",
            "orientation": "auto",
            "reduceOptions": {
              "calcs": [
                "lastNotNull"
              ],
              "fields": "",
              "values": false
            },
            "text": {},
            "textMode": "auto"
          },
          "pluginVersion": "7.5.1",
          "targets": [
            {
              "aggregator": "sum",
              "currentFilterGroupBy": false,
              "currentFilterKey": "",
              "currentFilterType": null,
              "currentFilterValue": "",
              "disableDownsampling": true,
              "downsampleAggregator": "noop",
              "downsampleFillPolicy": "none",
              "filters": [
                {
                  "filter": "$gateWayNode",
                  "groupBy": false,
                  "tagk": "node",
                  "type": "pm_filter"
                },
                {
                  "filter": "$afmFS",
                  "groupBy": false,
                  "tagk": "gpfs_fs_name",
                  "type": "pm_filter"
                }
              ],
              "metric": "gpfs_afm_fs_bytes_pending",
              "refId": "A"
            }
          ],
          "timeFrom": null,
          "timeShift": null,
          "title": "Total number of bytes pending",
          "type": "stat"
        }
      ],
      "title": "TREND CHARTS - Total number of bytes read/written from/to the remote system for   \"$afmFS\"   filesystem",
      "type": "row"
    },
    {
      "collapsed": true,
      "datasource": "${DS_SCALE_5.1.0-3}",
      "gridPos": {
        "h": 1,
        "w": 24,
        "x": 0,
        "y": 18
      },
      "id": 21,
      "panels": [
        {
          "datasource": "${DS_SCALE_CLUSTER_2_5.1.1.1}",
          "fieldConfig": {
            "defaults": {
              "color": {
                "mode": "palette-classic"
              },
              "mappings": [],
              "thresholds": {
                "mode": "absolute",
                "steps": [
                  {
                    "color": "green",
                    "value": null
                  },
                  {
                    "color": "red",
                    "value": 80
                  }
                ]
              },
              "unit": "short"
            },
            "overrides": []
          },
          "gridPos": {
            "h": 7,
            "w": 6,
            "x": 0,
            "y": 19
          },
          "id": 23,
          "options": {
            "colorMode": "value",
            "graphMode": "area",
            "justifyMode": "auto",
            "orientation": "auto",
            "reduceOptions": {
              "calcs": [
                "lastNotNull"
              ],
              "fields": "",
              "values": false
            },
            "text": {},
            "textMode": "auto"
          },
          "pluginVersion": "7.5.1",
          "targets": [
            {
              "aggregator": "sum",
              "currentFilterGroupBy": false,
              "currentFilterKey": "",
              "currentFilterType": null,
              "currentFilterValue": "",
              "disableDownsampling": true,
              "downsampleAggregator": "noop",
              "downsampleFillPolicy": "none",
              "filters": [
                {
                  "filter": "$afmFS",
                  "groupBy": false,
                  "tagk": "gpfs_fs_name",
                  "type": "pm_filter"
                },
                {
                  "filter": "$gateWayNode",
                  "groupBy": false,
                  "tagk": "node",
                  "type": "pm_filter"
                }
              ],
              "metric": "gpfs_afm_fs_ops_sync",
              "refId": "A"
            }
          ],
          "timeFrom": null,
          "timeShift": null,
          "title": " Total number of operations sync",
          "type": "stat"
        },
        {
          "datasource": "${DS_SCALE_CLUSTER_2_5.1.1.1}",
          "fieldConfig": {
            "defaults": {
              "color": {
                "mode": "palette-classic"
              },
              "mappings": [],
              "thresholds": {
                "mode": "absolute",
                "steps": [
                  {
                    "color": "green",
                    "value": null
                  },
                  {
                    "color": "red",
                    "value": 80
                  }
                ]
              },
              "unit": "short"
            },
            "overrides": []
          },
          "gridPos": {
            "h": 7,
            "w": 6,
            "x": 6,
            "y": 19
          },
          "id": 28,
          "options": {
            "colorMode": "value",
            "graphMode": "area",
            "justifyMode": "auto",
            "orientation": "auto",
            "reduceOptions": {
              "calcs": [
                "lastNotNull"
              ],
              "fields": "",
              "values": false
            },
            "text": {},
            "textMode": "auto"
          },
          "pluginVersion": "7.5.1",
          "targets": [
            {
              "aggregator": "sum",
              "currentFilterGroupBy": false,
              "currentFilterKey": "",
              "currentFilterType": null,
              "currentFilterValue": "",
              "disableDownsampling": true,
              "downsampleAggregator": "noop",
              "downsampleFillPolicy": "none",
              "filters": [
                {
                  "filter": "$afmFS",
                  "groupBy": false,
                  "tagk": "gpfs_fs_name",
                  "type": "pm_filter"
                },
                {
                  "filter": "$gateWayNode",
                  "groupBy": false,
                  "tagk": "node",
                  "type": "pm_filter"
                }
              ],
              "metric": "gpfs_afm_fs_ops_sent",
              "refId": "A"
            }
          ],
          "timeFrom": null,
          "timeShift": null,
          "title": " Total number of operations sent",
          "type": "stat"
        },
        {
          "datasource": "${DS_SCALE_CLUSTER_2_5.1.1.1}",
          "fieldConfig": {
            "defaults": {
              "color": {
                "mode": "palette-classic"
              },
              "mappings": [],
              "thresholds": {
                "mode": "absolute",
                "steps": [
                  {
                    "color": "green",
                    "value": null
                  },
                  {
                    "color": "red",
                    "value": 80
                  }
                ]
              },
              "unit": "short"
            },
            "overrides": []
          },
          "gridPos": {
            "h": 7,
            "w": 6,
            "x": 12,
            "y": 19
          },
          "id": 25,
          "options": {
            "colorMode": "value",
            "graphMode": "area",
            "justifyMode": "auto",
            "orientation": "auto",
            "reduceOptions": {
              "calcs": [
                "lastNotNull"
              ],
              "fields": "",
              "values": false
            },
            "text": {},
            "textMode": "auto"
          },
          "pluginVersion": "7.5.1",
          "targets": [
            {
              "aggregator": "sum",
              "currentFilterGroupBy": false,
              "currentFilterKey": "",
              "currentFilterType": null,
              "currentFilterValue": "",
              "disableDownsampling": true,
              "downsampleAggregator": "noop",
              "downsampleFillPolicy": "none",
              "filters": [
                {
                  "filter": "$gateWayNode",
                  "groupBy": false,
                  "tagk": "node",
                  "type": "pm_filter"
                },
                {
                  "filter": "$afmFS",
                  "groupBy": false,
                  "tagk": "gpfs_fs_name",
                  "type": "pm_filter"
                }
              ],
              "metric": "gpfs_afm_fs_ops_expired",
              "refId": "A"
            }
          ],
          "timeFrom": null,
          "timeShift": null,
          "title": " Total number of operations expired",
          "type": "stat"
        }
      ],
      "title": "TREND CHARTS - Number of operations that were sent to remote system \"$afmFS\" filesystem",
      "type": "row"
    },
    {
      "collapsed": true,
      "datasource": "${DS_SCALE_5.1.0-3}",
      "gridPos": {
        "h": 1,
        "w": 24,
        "x": 0,
        "y": 19
      },
      "id": 12,
      "panels": [
        {
          "datasource": "${DS_SCALE_CLUSTER_2_5.1.1.1}",
          "fieldConfig": {
            "defaults": {
              "color": {
                "mode": "continuous-GrYlRd"
              },
              "mappings": [],
              "thresholds": {
                "mode": "absolute",
                "steps": [
                  {
                    "color": "green",
                    "value": null
                  },
                  {
                    "color": "red",
                    "value": 80
                  }
                ]
              },
              "unit": "s"
            },
            "overrides": []
          },
          "gridPos": {
            "h": 7,
            "w": 6,
            "x": 0,
            "y": 20
          },
          "id": 8,
          "options": {
            "colorMode": "value",
            "graphMode": "area",
            "justifyMode": "auto",
            "orientation": "auto",
            "reduceOptions": {
              "calcs": [
                "max"
              ],
              "fields": "",
              "values": false
            },
            "text": {},
            "textMode": "auto"
          },
          "pluginVersion": "7.5.1",
          "targets": [
            {
              "aggregator": "avg",
              "alias": "",
              "currentFilterGroupBy": false,
              "currentFilterKey": "",
              "currentFilterType": null,
              "currentFilterValue": "",
              "disableDownsampling": true,
              "downsampleAggregator": "noop",
              "downsampleFillPolicy": "none",
              "downsampleInterval": "",
              "filters": [
                {
                  "filter": "$gateWayNode",
                  "groupBy": false,
                  "tagk": "node",
                  "type": "pm_filter"
                },
                {
                  "filter": "$afmFS",
                  "groupBy": false,
                  "tagk": "gpfs_fs_name",
                  "type": "pm_filter"
                }
              ],
              "metric": "gpfs_afm_fs_avg_time",
              "refId": "A"
            }
          ],
          "timeFrom": null,
          "timeShift": null,
          "title": "Average time in seconds",
          "type": "stat"
        },
        {
          "datasource": "${DS_SCALE_CLUSTER_2_5.1.1.1}",
          "fieldConfig": {
            "defaults": {
              "color": {
                "mode": "continuous-GrYlRd"
              },
              "mappings": [],
              "thresholds": {
                "mode": "absolute",
                "steps": [
                  {
                    "color": "green",
                    "value": null
                  },
                  {
                    "color": "red",
                    "value": 80
                  }
                ]
              },
              "unit": "s"
            },
            "overrides": []
          },
          "gridPos": {
            "h": 7,
            "w": 6,
            "x": 6,
            "y": 20
          },
          "id": 13,
          "options": {
            "colorMode": "value",
            "graphMode": "area",
            "justifyMode": "auto",
            "orientation": "auto",
            "reduceOptions": {
              "calcs": [
                "max"
              ],
              "fields": "",
              "values": false
            },
            "text": {},
            "textMode": "auto"
          },
          "pluginVersion": "7.5.1",
          "targets": [
            {
              "aggregator": "max",
              "alias": "",
              "currentFilterGroupBy": false,
              "currentFilterKey": "",
              "currentFilterType": null,
              "currentFilterValue": "",
              "disableDownsampling": true,
              "downsampleAggregator": "noop",
              "downsampleFillPolicy": "none",
              "downsampleInterval": "",
              "filters": [
                {
                  "filter": "$gateWayNode",
                  "groupBy": false,
                  "tagk": "node",
                  "type": "pm_filter"
                },
                {
                  "filter": "$afmFS",
                  "groupBy": false,
                  "tagk": "gpfs_fs_name",
                  "type": "pm_filter"
                }
              ],
              "metric": "gpfs_afm_fs_longest_time",
              "refId": "A"
            }
          ],
          "timeFrom": null,
          "timeShift": null,
          "title": "Longest time in seconds",
          "type": "stat"
        },
        {
          "datasource": "${DS_SCALE_CLUSTER_2_5.1.1.1}",
          "description": "",
          "fieldConfig": {
            "defaults": {
              "color": {
                "mode": "thresholds"
              },
              "mappings": [],
              "thresholds": {
                "mode": "absolute",
                "steps": [
                  {
                    "color": "green",
                    "value": null
                  },
                  {
                    "color": "red",
                    "value": 80
                  }
                ]
              },
              "unit": "s"
            },
            "overrides": []
          },
          "gridPos": {
            "h": 7,
            "w": 6,
            "x": 12,
            "y": 20
          },
          "id": 14,
          "options": {
            "colorMode": "value",
            "graphMode": "area",
            "justifyMode": "auto",
            "orientation": "auto",
            "reduceOptions": {
              "calcs": [
                "min"
              ],
              "fields": "",
              "values": false
            },
            "text": {},
            "textMode": "auto"
          },
          "pluginVersion": "7.5.1",
          "targets": [
            {
              "aggregator": "min",
              "alias": "",
              "currentFilterGroupBy": false,
              "currentFilterKey": "",
              "currentFilterType": null,
              "currentFilterValue": "",
              "disableDownsampling": true,
              "downsampleAggregator": "noop",
              "downsampleFillPolicy": "none",
              "downsampleInterval": "",
              "filters": [
                {
                  "filter": "$gateWayNode",
                  "groupBy": false,
                  "tagk": "node",
                  "type": "pm_filter"
                },
                {
                  "filter": "$afmFS",
                  "groupBy": false,
                  "tagk": "gpfs_fs_name",
                  "type": "pm_filter"
                }
              ],
              "metric": "gpfs_afm_fs_shortest_time",
              "refId": "A"
            }
          ],
          "timeFrom": null,
          "timeShift": null,
          "title": "Shortest time in seconds",
          "type": "stat"
        }
      ],
      "title": "TREND CHARTS - Time in seconds that a pending operation waited in the gateway queue before being sent to remote system for \"$afmFS\" filesystem.",
      "type": "row"
    },
    {
      "collapsed": true,
      "datasource": "${DS_SCALE_5.1.0-3}",
      "gridPos": {
        "h": 1,
        "w": 24,
        "x": 0,
        "y": 20
      },
      "id": 16,
      "panels": [
        {
          "datasource": "${DS_SCALE_CLUSTER_2_5.1.1.1}",
          "description": "",
          "fieldConfig": {
            "defaults": {
              "color": {
                "mode": "thresholds"
              },
              "mappings": [],
              "thresholds": {
                "mode": "absolute",
                "steps": [
                  {
                    "color": "green",
                    "value": null
                  },
                  {
                    "color": "red",
                    "value": 80
                  }
                ]
              },
              "unit": "short"
            },
            "overrides": []
          },
          "gridPos": {
            "h": 5,
            "w": 6,
            "x": 0,
            "y": 21
          },
          "id": 18,
          "options": {
            "colorMode": "value",
            "graphMode": "area",
            "justifyMode": "auto",
            "orientation": "auto",
            "reduceOptions": {
              "calcs": [
                "lastNotNull"
              ],
              "fields": "",
              "values": false
            },
            "text": {},
            "textMode": "auto"
          },
          "pluginVersion": "7.5.1",
          "targets": [
            {
              "aggregator": "max",
              "currentFilterGroupBy": false,
              "currentFilterKey": "",
              "currentFilterType": null,
              "currentFilterValue": "",
              "disableDownsampling": true,
              "downsampleAggregator": "noop",
              "downsampleFillPolicy": "none",
              "filters": [
                {
                  "filter": "$gateWayNode",
                  "groupBy": false,
                  "tagk": "node",
                  "type": "pm_filter"
                },
                {
                  "filter": "$afmFS",
                  "groupBy": false,
                  "tagk": "gpfs_fs_name",
                  "type": "pm_filter"
                }
              ],
              "metric": "gpfs_afm_fs_conn_esta",
              "refId": "A"
            }
          ],
          "title": "Total number  a connection was established ",
          "type": "stat"
        },
        {
          "datasource": "${DS_SCALE_CLUSTER_2_5.1.1.1}",
          "description": "",
          "fieldConfig": {
            "defaults": {
              "color": {
                "mode": "thresholds"
              },
              "mappings": [],
              "thresholds": {
                "mode": "absolute",
                "steps": [
                  {
                    "color": "green",
                    "value": null
                  },
                  {
                    "color": "red",
                    "value": 80
                  }
                ]
              },
              "unit": "short"
            },
            "overrides": []
          },
          "gridPos": {
            "h": 5,
            "w": 6,
            "x": 6,
            "y": 21
          },
          "id": 19,
          "options": {
            "colorMode": "value",
            "graphMode": "area",
            "justifyMode": "auto",
            "orientation": "auto",
            "reduceOptions": {
              "calcs": [
                "lastNotNull"
              ],
              "fields": "",
              "values": false
            },
            "text": {},
            "textMode": "auto"
          },
          "pluginVersion": "7.5.1",
          "targets": [
            {
              "aggregator": "max",
              "currentFilterGroupBy": false,
              "currentFilterKey": "",
              "currentFilterType": null,
              "currentFilterValue": "",
              "disableDownsampling": true,
              "downsampleAggregator": "noop",
              "downsampleFillPolicy": "none",
              "filters": [
                {
                  "filter": "$gateWayNode",
                  "groupBy": false,
                  "tagk": "node",
                  "type": "pm_filter"
                },
                {
                  "filter": "$afmFS",
                  "groupBy": false,
                  "tagk": "gpfs_fs_name",
                  "type": "pm_filter"
                }
              ],
              "metric": "gpfs_afm_fs_conn_broken",
              "refId": "A"
            }
          ],
          "title": "Total number  a connection was broken",
          "type": "stat"
        }
      ],
      "title": "Total number of times the connection to the remote system was established/ broken for the $afmFS filesystem",
      "type": "row"
    }
  ],
  "refresh": "10s",
  "schemaVersion": 27,
  "style": "dark",
  "tags": [
    "AFM"
  ],
  "templating": {
    "list": [
      {
        "current": {
          "selected": false,
          "text": "scale_cluster_2_5.1.1.1",
          "value": "scale_cluster_2_5.1.1.1"
        },
        "description": null,
        "error": null,
        "hide": 0,
        "includeAll": false,
        "label": null,
        "multi": false,
        "name": "cacheCluster",
        "options": [],
        "query": "opentsdb",
        "queryValue": "",
        "refresh": 1,
        "regex": "",
        "skipUrlSync": false,
        "type": "datasource"
      },
      {
        "allValue": null,
        "current": {},
        "datasource": "${DS_SCALE_CLUSTER_2_5.1.1.1}",
        "definition": "tag_values(gpfs_afm_fset_bytes_read, node)",
        "description": null,
        "error": null,
        "hide": 0,
        "includeAll": false,
        "label": "filter by Primary Gateway node",
        "multi": true,
        "name": "gateWayNode",
        "options": [],
        "query": "tag_values(gpfs_afm_fset_bytes_read, node)",
        "refresh": 2,
        "regex": "",
        "skipUrlSync": false,
        "sort": 0,
        "tagValuesQuery": "",
        "tags": [],
        "tagsQuery": "",
        "type": "query",
        "useTags": false
      },
      {
        "allValue": null,
        "current": {},
        "datasource": "${DS_SCALE_CLUSTER_2_5.1.1.1}",
        "definition": "tag_values(gpfs_afm_fs_ops_sent, gpfs_fs_name)",
        "description": null,
        "error": null,
        "hide": 0,
        "includeAll": false,
        "label": "filter by AFM Filesystem",
        "multi": false,
        "name": "afmFS",
        "options": [],
        "query": "tag_values(gpfs_afm_fs_ops_sent, gpfs_fs_name)",
        "refresh": 2,
        "regex": "",
        "skipUrlSync": false,
        "sort": 0,
        "tagValuesQuery": "",
        "tags": [],
        "tagsQuery": "",
        "type": "query",
        "useTags": false
      }
    ]
  },
  "time": {
    "from": "now-1h",
    "to": "now"
  },
  "timepicker": {},
  "timezone": "",
  "title": "AFM  FS view",
  "uid": "u240wk9Gk",
  "version": 94
}